smartasync/__init__.py
smartasync/core.py
smartasync-0.5.0.dist-info/licenses/LICENSE
smartasync-0.5.0.dist-info/METADATA
smartasync-0.5.0.dist-info/WHEEL
smartasync-0.5.0.dist-info/top_level.txt
smartasync-0.5.0.dist-info/RECORD
