Metadata-Version: 2.4
Name: smartasync
Version: 0.5.0
Summary: Unified sync/async API decorator with automatic context detection
Author-email: Giovanni Porcari <softwell@softwell.it>
License: MIT
Project-URL: Homepage, https://github.com/genropy/smartasync
Project-URL: Documentation, https://smartasync.readthedocs.io
Project-URL: Repository, https://github.com/genropy/smartasync
Project-URL: Bug Tracker, https://github.com/genropy/smartasync/issues
Keywords: async,sync,decorator,asyncio,context-detection,unified-api
Classifier: Development Status :: 4 - Beta
Classifier: Intended Audience :: Developers
Classifier: Programming Language :: Python :: 3
Classifier: Programming Language :: Python :: 3.10
Classifier: Programming Language :: Python :: 3.11
Classifier: Programming Language :: Python :: 3.12
Classifier: Topic :: Software Development :: Libraries :: Python Modules
Classifier: Framework :: AsyncIO
Classifier: Typing :: Typed
Requires-Python: >=3.10
License-File: LICENSE
Provides-Extra: dev
Requires-Dist: pytest>=7.0.0; extra == "dev"
Requires-Dist: pytest-asyncio>=0.21.0; extra == "dev"
Requires-Dist: pytest-cov>=4.0.0; extra == "dev"
Requires-Dist: black>=23.0.0; extra == "dev"
Requires-Dist: ruff>=0.1.0; extra == "dev"
Requires-Dist: mypy>=1.0.0; extra == "dev"
Provides-Extra: docs
Requires-Dist: sphinx>=8.0.0; extra == "docs"
Requires-Dist: sphinx-rtd-theme>=3.0.0; extra == "docs"
Requires-Dist: sphinx-autodoc-typehints>=3.0.0; extra == "docs"
Requires-Dist: myst-parser>=4.0.0; extra == "docs"
Requires-Dist: sphinxcontrib-mermaid>=1.0.0; extra == "docs"
Provides-Extra: all
Requires-Dist: pytest>=7.0.0; extra == "all"
Requires-Dist: pytest-asyncio>=0.21.0; extra == "all"
Requires-Dist: pytest-cov>=4.0.0; extra == "all"
Requires-Dist: black>=23.0.0; extra == "all"
Requires-Dist: ruff>=0.1.0; extra == "all"
Requires-Dist: mypy>=1.0.0; extra == "all"
Requires-Dist: sphinx>=8.0.0; extra == "all"
Requires-Dist: sphinx-rtd-theme>=3.0.0; extra == "all"
Requires-Dist: sphinx-autodoc-typehints>=3.0.0; extra == "all"
Requires-Dist: myst-parser>=4.0.0; extra == "all"
Requires-Dist: sphinxcontrib-mermaid>=1.0.0; extra == "all"
Dynamic: license-file
